{"files":{"index.html":{"frameworks":["pg.asset.manager","pg.code-validator","pg.project.items","pg.insight.events","pg.image.overlay","pg.css.grid","pg.fontawesome","bs4","pg.html","pg.components"],"last_page_width":1024},"pricing.html":{"frameworks":["pg.asset.manager","pg.insight.events","pg.project.items","pg.css.grid","pg.code-validator","pg.image.overlay","bs4","pg.html","pg.components"],"last_page_width":1024}},"breakpoints":["576px","768px","992px","1200px"],"frameworks":["pg.asset.manager","pg.code-validator","pg.project.items","pg.insight.events","pg.image.overlay","pg.css.grid","pg.fontawesome","bs4","pg.html","pg.components"],"cs-for-overrides":"style.css"}